{"stats":{"minecraft:picked_up":{"minecraft:wooden_axe":1,"minecraft:flower_pot":1,"minecraft:prismarine_shard":19,"minecraft:magenta_carpet":7,"minecraft:lead":1,"minecraft:diamond_sword":19,"minecraft:light":67,"minecraft:music_disc_cat":1,"minecraft:string":2,"minecraft:pufferfish":2,"minecraft:diamond_leggings":6,"minecraft:gold_nugget":84,"minecraft:written_book":6,"minecraft:enchanted_golden_apple":565,"minecraft:dark_oak_door":1,"minecraft:golden_helmet":2,"minecraft:music_disc_blocks":2,"minecraft:big_dripleaf":2,"minecraft:green_bed":4,"minecraft:orange_bed":2,"minecraft:stone_sword":2,"minecraft:command_block":1,"minecraft:tropical_fish":14,"minecraft:red_tulip":1,"minecraft:feather":1,"minecraft:cooked_beef":64,"minecraft:iron_door":3,"minecraft:water_bucket":1,"minecraft:lantern":44,"minecraft:diamond_helmet":5,"minecraft:rabbit":1,"minecraft:dispenser":1,"minecraft:lever":2,"minecraft:writable_book":4,"minecraft:blue_banner":1,"minecraft:nether_wart":7,"minecraft:cornflower":40,"minecraft:elytra":1,"minecraft:compass":1,"minecraft:netherite_sword":3,"minecraft:music_disc_otherside":1,"minecraft:beef":4,"minecraft:poppy":1,"minecraft:minecart":1,"minecraft:birch_sapling":6,"minecraft:diamond_hoe":1,"minecraft:oak_door":5,"minecraft:glow_item_frame":1,"minecraft:music_disc_mellohi":2,"minecraft:carrot":3,"minecraft:redstone":8,"minecraft:prismarine_crystals":11,"minecraft:blue_carpet":7,"minecraft:diamond_chestplate":6,"minecraft:stone_shovel":2,"minecraft:diamond_boots":7,"minecraft:totem_of_undying":1,"minecraft:polished_blackstone":3,"minecraft:mutton":5,"minecraft:rail":1,"minecraft:oxeye_daisy":168,"minecraft:red_mushroom":1,"minecraft:filled_map":117,"minecraft:oak_log":5,"minecraft:light_blue_banner":8,"minecraft:music_disc_far":2,"minecraft:stone_pickaxe":2,"minecraft:iron_sword":1,"minecraft:flowering_azalea":2,"minecraft:sweet_berries":13,"minecraft:red_wool":1,"minecraft:gravel":24,"minecraft:firework_rocket":34,"minecraft:stone_axe":2,"minecraft:diamond_axe":9,"minecraft:birch_sign":2,"minecraft:ender_pearl":383,"minecraft:music_disc_strad":3,"minecraft:wheat":8,"minecraft:potion":11,"minecraft:iron_leggings":1,"minecraft:oak_sign":4,"minecraft:redstone_torch":7,"minecraft:azalea":1,"minecraft:iron_boots":1,"minecraft:stick":5,"minecraft:torch":6,"minecraft:porkchop":2,"minecraft:pointed_dripstone":7,"minecraft:rotten_flesh":20,"minecraft:music_disc_ward":3,"minecraft:music_disc_wait":5,"minecraft:cod":8,"minecraft:cobblestone":2,"minecraft:potato":2,"minecraft:tuff":4,"minecraft:dirt":13,"minecraft:bone":2,"minecraft:bow":6,"minecraft:wheat_seeds":45,"minecraft:bell":8,"minecraft:netherite_axe":1,"minecraft:powered_rail":2,"minecraft:stone_hoe":1,"minecraft:music_disc_13":7,"minecraft:spectral_arrow":296,"minecraft:shulker_box":2,"minecraft:yellow_carpet":3,"minecraft:diamond":6,"minecraft:netherite_helmet":2,"minecraft:polished_blackstone_button":13,"minecraft:bone_meal":2,"minecraft:golden_apple":65,"minecraft:spruce_sign":1,"minecraft:emerald":221,"minecraft:oak_sapling":4,"minecraft:azure_bluet":20,"minecraft:chicken":1,"minecraft:ladder":5,"minecraft:gold_block":64,"minecraft:shield":11,"minecraft:moss_carpet":4,"minecraft:iron_axe":2,"minecraft:item_frame":68,"minecraft:blue_orchid":6,"minecraft:detector_rail":1,"minecraft:dark_prismarine_stairs":1,"minecraft:player_head":7,"minecraft:copper_ingot":1,"minecraft:stone_button":7,"minecraft:music_disc_11":1,"minecraft:light_blue_bed":3,"minecraft:stone_pressure_plate":2,"minecraft:dark_oak_planks":1,"minecraft:arrow":65,"minecraft:nether_bricks":1,"minecraft:wet_sponge":1,"minecraft:netherite_boots":2,"minecraft:dark_oak_button":12,"minecraft:leather":2,"minecraft:music_disc_stal":5,"minecraft:gunpowder":6,"minecraft:gray_carpet":1,"minecraft:acacia_sapling":1,"minecraft:music_disc_chirp":2,"minecraft:pink_bed":1,"minecraft:dandelion":2,"minecraft:soul_torch":1,"minecraft:white_bed":1,"minecraft:spruce_door":12,"minecraft:music_disc_mall":3,"minecraft:mossy_cobblestone_stairs":1,"minecraft:coal":2},"minecraft:custom":{"minecraft:interact_with_crafting_table":25,"minecraft:open_barrel":5,"minecraft:bell_ring":56,"minecraft:eat_cake_slice":2,"minecraft:leave_game":236,"minecraft:time_since_death":187221,"minecraft:play_time":6000567,"minecraft:deaths":12,"minecraft:jump":5442,"minecraft:interact_with_furnace":5,"minecraft:play_record":38,"minecraft:traded_with_villager":35,"minecraft:sleep_in_bed":3,"minecraft:damage_dealt":66755,"minecraft:use_cauldron":8,"minecraft:inspect_dispenser":19,"minecraft:horse_one_cm":6375,"minecraft:interact_with_smithing_table":2,"minecraft:interact_with_anvil":37,"minecraft:inspect_hopper":8,"minecraft:target_hit":1,"minecraft:sneak_time":248094,"minecraft:interact_with_lectern":18,"minecraft:interact_with_blast_furnace":5,"minecraft:total_world_time":6000783,"minecraft:interact_with_stonecutter":1,"minecraft:time_since_rest":187242,"minecraft:swim_one_cm":10848,"minecraft:fly_one_cm":91252344,"minecraft:open_chest":328,"minecraft:fall_one_cm":29793,"minecraft:open_shulker_box":107,"minecraft:damage_resisted":663,"minecraft:sprint_one_cm":1484516,"minecraft:drop":399,"minecraft:talked_to_villager":119,"minecraft:interact_with_brewingstand":7,"minecraft:walk_on_water_one_cm":577370,"minecraft:interact_with_loom":3,"minecraft:open_enderchest":14,"minecraft:interact_with_beacon":27,"minecraft:crouch_one_cm":56844,"minecraft:mob_kills":356,"minecraft:fill_cauldron":14,"minecraft:interact_with_campfire":12,"minecraft:climb_one_cm":68272,"minecraft:walk_one_cm":3306979,"minecraft:raid_win":1,"minecraft:walk_under_water_one_cm":2412669,"minecraft:boat_one_cm":1650,"minecraft:pot_flower":111,"minecraft:damage_taken":7070,"minecraft:damage_absorbed":2126,"minecraft:trigger_trapped_chest":158,"minecraft:minecart_one_cm":518,"minecraft:aviate_one_cm":2626576},"minecraft:crafted":{"minecraft:player_head":10,"minecraft:diamond":72,"minecraft:leather_helmet":1,"minecraft:potion":7,"minecraft:paper":5,"minecraft:shield":1,"minecraft:iron_ingot":207,"minecraft:leather_boots":1,"minecraft:filled_map":10,"minecraft:bell":1,"minecraft:stone_axe":12},"minecraft:dropped":{"minecraft:iron_sword":1,"minecraft:cooked_beef":16,"minecraft:glow_ink_sac":1,"minecraft:dark_oak_slab":1,"minecraft:glow_item_frame":1,"minecraft:cracked_stone_bricks":2,"minecraft:elytra":1,"minecraft:item_frame":13,"minecraft:emerald":67,"minecraft:dirt":3,"minecraft:netherite_boots":4,"minecraft:chain":1,"minecraft:gold_nugget":5,"minecraft:bone_meal":1,"minecraft:bone":2,"minecraft:oak_door":1,"minecraft:compass":2,"minecraft:pink_bed":1,"minecraft:cobbled_deepslate":1,"minecraft:netherite_sword":4,"minecraft:obsidian":1,"minecraft:grindstone":1,"minecraft:rotten_flesh":1,"minecraft:end_stone":1,"minecraft:command_block_minecart":1,"minecraft:tipped_arrow":123,"minecraft:hopper":1,"minecraft:ladder":1,"minecraft:spruce_slab":1,"minecraft:campfire":1,"minecraft:stone_brick_stairs":1,"minecraft:netherite_pickaxe":1,"minecraft:wheat_seeds":3,"minecraft:cobbled_deepslate_stairs":2,"minecraft:polished_blackstone":1,"minecraft:netherite_helmet":3,"minecraft:netherite_chestplate":1,"minecraft:oak_fence":2,"minecraft:barrier":1,"minecraft:cobblestone":5,"minecraft:command_block":1,"minecraft:spruce_door":2,"minecraft:polished_blackstone_button":1,"minecraft:yellow_carpet":3,"minecraft:golden_apple":1,"minecraft:lava_bucket":2,"minecraft:cobweb":1,"minecraft:lodestone":1,"minecraft:wooden_axe":6,"minecraft:potion":1,"minecraft:dead_bush":1,"minecraft:mossy_cobblestone_stairs":1,"minecraft:smooth_stone":1,"minecraft:stone_brick_slab":1,"minecraft:moss_carpet":2,"minecraft:player_head":16,"minecraft:soul_torch":3,"minecraft:cobblestone_wall":1,"minecraft:smooth_stone_slab":1,"minecraft:deepslate":3,"minecraft:iron_boots":1,"minecraft:cobbled_deepslate_slab":1,"minecraft:glow_lichen":1,"minecraft:diamond_sword":4,"minecraft:stone":2,"minecraft:potato":1,"minecraft:shroomlight":1,"minecraft:cobblestone_slab":1,"minecraft:spruce_trapdoor":1,"minecraft:diamond_pickaxe":1,"minecraft:redstone_torch":2,"minecraft:stone_bricks":3,"minecraft:bow":1,"minecraft:red_sand":1,"minecraft:blue_orchid":3,"minecraft:bell":3,"minecraft:dark_prismarine":2,"minecraft:nether_brick_stairs":1,"minecraft:dark_oak_stairs":1,"minecraft:oak_log":3,"minecraft:ender_pearl":15,"minecraft:dark_oak_sapling":1,"minecraft:lantern":5,"minecraft:red_wool":4,"minecraft:mossy_cobblestone_wall":1,"minecraft:spruce_leaves":2,"minecraft:cracked_polished_blackstone_bricks":2,"minecraft:ice":2,"minecraft:dispenser":2,"minecraft:cornflower":2,"minecraft:mutton":3,"minecraft:blaze_spawn_egg":1,"minecraft:wet_sponge":1,"minecraft:polished_blackstone_bricks":1,"minecraft:gravel":8,"minecraft:blackstone":1,"minecraft:carrot":4,"minecraft:chiseled_stone_bricks":1,"minecraft:oak_fence_gate":1,"minecraft:petrified_oak_slab":4,"minecraft:stone_brick_wall":2,"minecraft:chest":1,"minecraft:iron_bars":1,"minecraft:basalt":3,"minecraft:arrow":10,"minecraft:written_book":1,"minecraft:netherrack":2,"minecraft:splash_potion":2,"minecraft:firework_rocket":33,"minecraft:spawner":64,"minecraft:stone_hoe":1,"minecraft:water_bucket":6,"minecraft:oak_slab":1,"minecraft:magenta_carpet":1,"minecraft:golden_helmet":2,"minecraft:mossy_cobblestone":1,"minecraft:netherite_axe":1,"minecraft:amethyst_block":1,"minecraft:tropical_fish":1,"minecraft:spruce_stairs":3,"minecraft:grass_block":5,"minecraft:milk_bucket":1,"minecraft:torch":1,"minecraft:map":7,"minecraft:iron_leggings":1,"minecraft:stonecutter":1,"minecraft:dandelion":2,"minecraft:oak_trapdoor":1,"minecraft:dark_prismarine_stairs":3,"minecraft:nether_wart":7,"minecraft:coarse_dirt":1,"minecraft:oxidized_cut_copper_stairs":1,"minecraft:dirt_path":1,"minecraft:totem_of_undying":1,"minecraft:acacia_leaves":1,"minecraft:glass_pane":1,"minecraft:flint_and_steel":1,"minecraft:netherite_leggings":2,"minecraft:cut_red_sandstone":1,"minecraft:light":256,"minecraft:filled_map":3,"minecraft:shield":1,"minecraft:orange_terracotta":1,"minecraft:andesite":1,"minecraft:oak_sapling":1},"minecraft:killed_by":{"minecraft:zombie_villager":1,"minecraft:zombie":6},"minecraft:killed":{"minecraft:shulker":1,"minecraft:pufferfish":1,"minecraft:skeleton":15,"minecraft:guardian":52,"minecraft:chicken":1,"minecraft:tropical_fish":11,"minecraft:elder_guardian":2,"minecraft:iron_golem":1,"minecraft:zombie":19,"minecraft:cow":7,"minecraft:evoker":1,"minecraft:endermite":6,"minecraft:vindicator":1,"minecraft:horse":2,"minecraft:enderman":47,"minecraft:zombified_piglin":44,"minecraft:spider":9,"minecraft:bee":1,"minecraft:axolotl":13,"minecraft:illusioner":1,"minecraft:turtle":2,"minecraft:zombie_villager":22,"minecraft:creeper":13,"minecraft:sheep":2,"minecraft:stray":1,"minecraft:slime":17,"minecraft:phantom":7,"minecraft:villager":55},"minecraft:used":{"minecraft:peony":12,"minecraft:moss_block":72,"minecraft:music_disc_far":2,"minecraft:jack_o_lantern":2,"minecraft:writable_book":24,"minecraft:chiseled_deepslate":23,"minecraft:smooth_quartz_slab":31,"minecraft:spruce_slab":820,"minecraft:polished_blackstone":74,"minecraft:ladder":41,"minecraft:poppy":96,"minecraft:elytra":1,"minecraft:chest":119,"minecraft:stone":1204,"minecraft:quartz_stairs":79,"minecraft:warped_sign":1,"minecraft:farmland":22,"minecraft:tube_coral":11,"minecraft:pink_candle":2,"minecraft:soul_sand":78,"minecraft:weathered_copper":7,"minecraft:lily_of_the_valley":12,"minecraft:cut_copper":134,"minecraft:blue_stained_glass":97,"minecraft:jungle_slab":3,"minecraft:allium":2,"minecraft:cracked_deepslate_tiles":2,"minecraft:deepslate_brick_slab":41,"minecraft:yellow_candle":5,"minecraft:magenta_candle":3,"minecraft:azure_bluet":498,"minecraft:stripped_spruce_log":242,"minecraft:spruce_boat":2,"minecraft:polished_blackstone_slab":1,"minecraft:packed_ice":1,"minecraft:lava_bucket":169,"minecraft:netherite_shovel":1853,"minecraft:quartz_pillar":32,"minecraft:villager_spawn_egg":55,"minecraft:red_wool":1637,"minecraft:black_stained_glass_pane":4,"minecraft:grass_block":2018,"minecraft:deepslate_copper_ore":4,"minecraft:birch_sapling":14,"minecraft:music_disc_ward":3,"minecraft:polished_andesite_stairs":333,"minecraft:quartz_block":565,"minecraft:wet_sponge":3,"minecraft:music_disc_chirp":2,"minecraft:netherite_hoe":1289,"minecraft:dark_oak_leaves":28,"minecraft:dark_oak_slab":338,"minecraft:waxed_weathered_cut_copper":1,"minecraft:music_disc_wait":4,"minecraft:dark_oak_button":123,"minecraft:stone_brick_stairs":658,"minecraft:blue_banner":24,"minecraft:music_disc_stal":5,"minecraft:red_stained_glass_pane":7,"minecraft:bow":267,"minecraft:snow":196,"minecraft:sweet_berries":7,"minecraft:guardian_spawn_egg":1,"minecraft:oak_sapling":19,"minecraft:furnace":14,"minecraft:gray_banner":3,"minecraft:potato":409,"minecraft:dragon_head":3,"minecraft:green_stained_glass_pane":2,"minecraft:seagrass":117,"minecraft:dark_prismarine_stairs":80,"minecraft:deepslate_brick_wall":37,"minecraft:mossy_stone_bricks":38,"minecraft:end_stone_bricks":3,"minecraft:damaged_anvil":7,"minecraft:cow_spawn_egg":8,"minecraft:spruce_door":60,"minecraft:stripped_birch_log":35,"minecraft:red_stained_glass":2,"minecraft:blackstone_stairs":2,"minecraft:powered_rail":55,"minecraft:prismarine":21,"minecraft:orange_tulip":1,"minecraft:blackstone":46,"minecraft:mossy_stone_brick_stairs":27,"minecraft:composter":17,"minecraft:clay":1,"minecraft:smooth_quartz_stairs":64,"minecraft:oak_leaves":879,"minecraft:golden_apple":19,"minecraft:respawn_anchor":1,"minecraft:glow_berries":44,"minecraft:dark_oak_trapdoor":19,"minecraft:blue_dye":10,"minecraft:sand":99,"minecraft:blast_furnace":5,"minecraft:acacia_leaves":20,"minecraft:blue_ice":1,"minecraft:chiseled_quartz_block":24,"minecraft:gray_concrete":1,"minecraft:deepslate_brick_stairs":38,"minecraft:purple_concrete_powder":16,"minecraft:lightning_rod":6,"minecraft:deepslate_tiles":21,"minecraft:crying_obsidian":2,"minecraft:birch_slab":3,"minecraft:deepslate_iron_ore":3,"minecraft:stone_button":89,"minecraft:lectern":18,"minecraft:spore_blossom":1,"minecraft:cut_red_sandstone":25,"minecraft:flowering_azalea_leaves":30,"minecraft:lilac":23,"minecraft:polished_andesite_slab":781,"minecraft:soul_lantern":40,"minecraft:magenta_stained_glass_pane":3,"minecraft:green_candle":4,"minecraft:diamond_sword":363,"minecraft:coal_block":2,"minecraft:exposed_cut_copper":3,"minecraft:smithing_table":5,"minecraft:dark_oak_fence":11,"minecraft:white_stained_glass":14,"minecraft:birch_log":10,"minecraft:ice":63,"minecraft:compass":2,"minecraft:oak_trapdoor":572,"minecraft:polished_blackstone_brick_slab":1,"minecraft:enchanting_table":17,"minecraft:iron_bars":87,"minecraft:acacia_log":7,"minecraft:brain_coral_fan":25,"minecraft:dead_bush":5,"minecraft:carved_pumpkin":1,"minecraft:red_concrete":1,"minecraft:armor_stand":10,"minecraft:stripped_warped_stem":1,"minecraft:tinted_glass":108,"minecraft:polished_blackstone_wall":6,"minecraft:structure_block":3,"minecraft:netherrack":36,"minecraft:orange_stained_glass":1,"minecraft:bee_spawn_egg":1,"minecraft:orange_bed":7,"minecraft:torch":277,"minecraft:dragon_egg":1,"minecraft:brewing_stand":21,"minecraft:ancient_debris":8,"minecraft:anvil":27,"minecraft:warped_wart_block":2,"minecraft:target":2,"minecraft:chorus_flower":11,"minecraft:stone_stairs":138,"minecraft:dead_tube_coral":2,"minecraft:golden_shovel":444,"minecraft:glow_lichen":172,"minecraft:nether_brick_stairs":38,"minecraft:oak_fence_gate":201,"minecraft:polished_diorite":134,"minecraft:orange_candle":10,"minecraft:small_dripleaf":6,"minecraft:shroomlight":60,"minecraft:mossy_cobblestone_stairs":35,"minecraft:music_disc_mellohi":2,"minecraft:red_shulker_box":1,"minecraft:sea_lantern":362,"minecraft:flowering_azalea":11,"minecraft:chipped_anvil":5,"minecraft:iron_block":731,"minecraft:light_weighted_pressure_plate":3,"minecraft:rooted_dirt":99,"minecraft:spruce_button":67,"minecraft:brick_stairs":4,"minecraft:polished_deepslate_wall":28,"minecraft:spawner":15,"minecraft:chicken_spawn_egg":1,"minecraft:smooth_quartz":99,"minecraft:pink_stained_glass_pane":1,"minecraft:prismarine_slab":4,"minecraft:barrel":23,"minecraft:blaze_spawn_egg":1,"minecraft:diamond_chestplate":1,"minecraft:basalt":102,"minecraft:glowstone":720,"minecraft:raw_copper_block":12,"minecraft:magenta_wool":13,"minecraft:tall_grass":3,"minecraft:iron_trapdoor":157,"minecraft:oxidized_copper":2,"minecraft:podzol":1,"minecraft:acacia_wood":88,"minecraft:trapped_chest":17,"minecraft:cobbled_deepslate":56,"minecraft:observer":4,"minecraft:orange_terracotta":47,"minecraft:golden_axe":5,"minecraft:hanging_roots":16,"minecraft:horn_coral_fan":5,"minecraft:command_block_minecart":20,"minecraft:pointed_dripstone":214,"minecraft:calcite":1,"minecraft:wheat_seeds":709,"minecraft:water_bucket":3246,"minecraft:dirt_path":525,"minecraft:prismarine_brick_slab":6,"minecraft:birch_planks":4,"minecraft:lead":3,"minecraft:lime_wool":12,"minecraft:bubble_coral_fan":24,"minecraft:cartography_table":18,"minecraft:cauldron":25,"minecraft:fletching_table":6,"minecraft:glow_ink_sac":22,"minecraft:spruce_fence_gate":56,"minecraft:gold_ore":1,"minecraft:deepslate_bricks":393,"minecraft:polished_blackstone_bricks":54,"minecraft:conduit":3,"minecraft:cracked_stone_bricks":198,"minecraft:waxed_exposed_copper":3,"minecraft:brown_dye":3,"minecraft:mossy_cobblestone":102,"minecraft:diamond_block":60,"minecraft:rail":116,"minecraft:comparator":3,"minecraft:vine":36,"minecraft:oak_slab":447,"minecraft:crafting_table":23,"minecraft:crimson_trapdoor":3,"minecraft:red_bed":4,"minecraft:birch_sign":66,"minecraft:white_bed":6,"minecraft:campfire":35,"minecraft:dark_oak_fence_gate":17,"minecraft:fire_coral":11,"minecraft:endermite_spawn_egg":6,"minecraft:cake":1,"minecraft:spruce_log":49,"minecraft:music_disc_strad":3,"minecraft:oak_log":1599,"minecraft:amethyst_cluster":16,"minecraft:light_blue_candle":8,"minecraft:blue_stained_glass_pane":20,"minecraft:dark_prismarine":132,"minecraft:yellow_dye":2,"minecraft:ender_eye":44,"minecraft:light":154,"minecraft:diamond_pickaxe":4,"minecraft:cornflower":193,"minecraft:oxeye_daisy":698,"minecraft:warped_trapdoor":5,"minecraft:diamond_shovel":6,"minecraft:oak_button":5,"minecraft:spruce_trapdoor":138,"minecraft:spruce_sapling":5,"minecraft:music_disc_blocks":2,"minecraft:crimson_nylium":39,"minecraft:crimson_sign":2,"minecraft:blue_carpet":14,"minecraft:green_carpet":1,"minecraft:chiseled_stone_bricks":60,"minecraft:azalea_leaves":144,"minecraft:cobblestone":3458,"minecraft:potion":13,"minecraft:purple_bed":3,"minecraft:andesite_stairs":4,"minecraft:glass_pane":228,"minecraft:black_candle":17,"minecraft:end_portal_frame":71,"minecraft:stripped_oak_log":35,"minecraft:kelp":172,"minecraft:dandelion":49,"minecraft:candle":25,"minecraft:jukebox":7,"minecraft:diamond_leggings":1,"minecraft:light_blue_banner":38,"minecraft:moss_carpet":64,"minecraft:light_blue_stained_glass_pane":1,"minecraft:waxed_exposed_cut_copper":8,"minecraft:red_sand":29,"minecraft:light_gray_dye":5,"minecraft:purple_candle":17,"minecraft:iron_shovel":42,"minecraft:polished_deepslate":6,"minecraft:dead_tube_coral_fan":3,"minecraft:oak_sign":74,"minecraft:axolotl_spawn_egg":20,"minecraft:zombie_spawn_egg":1,"minecraft:vex_spawn_egg":1,"minecraft:bubble_coral":8,"minecraft:grass":26,"minecraft:bell":7,"minecraft:player_head":200,"minecraft:mossy_stone_brick_slab":32,"minecraft:soul_campfire":33,"minecraft:spruce_leaves":70,"minecraft:sculk_sensor":1,"minecraft:white_candle":4,"minecraft:debug_stick":170,"minecraft:oxidized_cut_copper":1,"minecraft:stray_spawn_egg":1,"minecraft:nether_bricks":8,"minecraft:carrot":206,"minecraft:deepslate_tile_slab":5,"minecraft:furnace_minecart":1,"minecraft:music_disc_13":7,"minecraft:tuff":82,"minecraft:music_disc_11":1,"minecraft:beehive":10,"minecraft:axolotl_bucket":2,"minecraft:milk_bucket":1,"minecraft:obsidian":20,"minecraft:big_dripleaf":10,"minecraft:glass":299,"minecraft:waxed_oxidized_copper":2,"minecraft:crimson_button":12,"minecraft:bricks":7,"minecraft:quartz_slab":30,"minecraft:lantern":240,"minecraft:blue_orchid":49,"minecraft:green_wool":5,"minecraft:warped_nylium":22,"minecraft:light_blue_bed":4,"minecraft:mossy_cobblestone_slab":73,"minecraft:tropical_fish_spawn_egg":52,"minecraft:raw_gold_block":13,"minecraft:stone_bricks":1580,"minecraft:item_frame":158,"minecraft:bedrock":5,"minecraft:birch_button":8,"minecraft:deepslate_diamond_ore":1,"minecraft:red_carpet":19,"minecraft:repeater":68,"minecraft:redstone_lamp":23,"minecraft:red_nether_brick_wall":7,"minecraft:magma_block":13,"minecraft:brown_carpet":4,"minecraft:hay_block":54,"minecraft:horn_coral":10,"minecraft:written_book":23,"minecraft:scaffolding":19,"minecraft:blue_shulker_box":5,"minecraft:oxidized_cut_copper_stairs":5,"minecraft:gray_bed":1,"minecraft:beetroot_seeds":130,"minecraft:polished_diorite_stairs":127,"minecraft:gold_block":195,"minecraft:fire_coral_fan":25,"minecraft:polished_blackstone_stairs":3,"minecraft:stripped_spruce_wood":142,"minecraft:chiseled_polished_blackstone":4,"minecraft:dark_oak_stairs":300,"minecraft:end_rod":50,"minecraft:tube_coral_fan":26,"minecraft:diamond_boots":1,"minecraft:birch_leaves":1,"minecraft:elder_guardian_spawn_egg":1,"minecraft:dark_oak_sign":3,"minecraft:oak_planks":1117,"minecraft:prismarine_stairs":2,"minecraft:polished_diorite_slab":47,"minecraft:redstone_block":33,"minecraft:structure_void":1,"minecraft:diamond_axe":4,"minecraft:sugar_cane":9,"minecraft:white_wool":157,"minecraft:brain_coral":10,"minecraft:golden_hoe":16,"minecraft:infested_chiseled_stone_bricks":90,"minecraft:lime_stained_glass_pane":5,"minecraft:loom":1,"minecraft:light_blue_wool":22,"minecraft:sponge":7,"minecraft:stone_brick_wall":115,"minecraft:shulker_spawn_egg":1,"minecraft:black_bed":2,"minecraft:end_stone":42,"minecraft:cobbled_deepslate_stairs":17,"minecraft:exposed_copper":4,"minecraft:redstone_torch":88,"minecraft:sticky_piston":33,"minecraft:lever":28,"minecraft:blue_glazed_terracotta":7,"minecraft:firework_rocket":1308,"minecraft:daylight_detector":4,"minecraft:gray_shulker_box":1,"minecraft:music_disc_mall":4,"minecraft:barrier":522,"minecraft:bread":5,"minecraft:string":1,"minecraft:light_gray_candle":2,"minecraft:iron_door":39,"minecraft:prismarine_wall":10,"minecraft:deepslate":128,"minecraft:gravel":460,"minecraft:evoker_spawn_egg":1,"minecraft:blue_candle":10,"minecraft:light_blue_concrete_powder":30,"minecraft:grindstone":3,"minecraft:stripped_oak_wood":38,"minecraft:waxed_oxidized_cut_copper_stairs":2,"minecraft:andesite":86,"minecraft:chain":242,"minecraft:smooth_stone_slab":108,"minecraft:mossy_cobblestone_wall":12,"minecraft:chest_minecart":2,"minecraft:tropical_fish_bucket":1,"minecraft:coarse_dirt":2264,"minecraft:warped_button":9,"minecraft:chorus_plant":64,"minecraft:bone_meal":184,"minecraft:cobweb":48,"minecraft:azalea":69,"minecraft:oak_fence":429,"minecraft:petrified_oak_slab":168,"minecraft:orange_concrete_powder":16,"minecraft:netherite_sword":237,"minecraft:rose_bush":39,"minecraft:waxed_weathered_copper":2,"minecraft:music_disc_otherside":1,"minecraft:flint_and_steel":61,"minecraft:white_tulip":7,"minecraft:cracked_deepslate_bricks":73,"minecraft:redstone":301,"minecraft:pufferfish_spawn_egg":7,"minecraft:spruce_planks":600,"minecraft:ender_chest":17,"minecraft:deepslate_gold_ore":1,"minecraft:stone_hoe":1,"minecraft:cut_copper_stairs":17,"minecraft:dirt":298,"minecraft:red_nether_brick_slab":8,"minecraft:white_carpet":2,"minecraft:hopper":51,"minecraft:prismarine_bricks":137,"minecraft:spruce_stairs":821,"minecraft:cobblestone_wall":75,"minecraft:diamond_helmet":1,"minecraft:shulker_box":8,"minecraft:raw_iron_block":22,"minecraft:warped_pressure_plate":2,"minecraft:spruce_fence":147,"minecraft:light_blue_stained_glass":1,"minecraft:andesite_wall":31,"minecraft:iron_hoe":3,"minecraft:purple_stained_glass_pane":7,"minecraft:stone_brick_slab":827,"minecraft:dark_oak_planks":184,"minecraft:wooden_axe":3,"minecraft:red_tulip":308,"minecraft:bookshelf":96,"minecraft:waxed_cut_copper":6,"minecraft:yellow_stained_glass":21,"minecraft:oak_stairs":543,"minecraft:acacia_slab":1,"minecraft:red_candle":19,"minecraft:polished_blackstone_brick_stairs":5,"minecraft:crimson_planks":38,"minecraft:light_gray_wool":5,"minecraft:weathered_cut_copper":3,"minecraft:black_stained_glass":33,"minecraft:emerald_block":8,"minecraft:soul_soil":36,"minecraft:lime_stained_glass":3,"minecraft:deepslate_tile_stairs":3,"minecraft:white_stained_glass_pane":47,"minecraft:minecart":6,"minecraft:stone_pressure_plate":40,"minecraft:granite_wall":3,"minecraft:red_dye":2,"minecraft:powder_snow_bucket":2,"minecraft:brown_candle":4,"minecraft:turtle_egg":12,"minecraft:enchanted_golden_apple":17,"minecraft:light_gray_bed":12,"minecraft:brown_bed":2,"minecraft:cobbled_deepslate_wall":14,"minecraft:turtle_spawn_egg":3,"minecraft:quartz_bricks":25,"minecraft:pink_tulip":11,"minecraft:amethyst_block":77,"minecraft:cobblestone_stairs":745,"minecraft:snow_block":42,"minecraft:lodestone":18,"minecraft:cyan_candle":7,"minecraft:polished_andesite":449,"minecraft:baked_potato":2,"minecraft:red_nether_bricks":24,"minecraft:blue_wool":121,"minecraft:copper_block":271,"minecraft:black_shulker_box":1,"minecraft:spruce_sign":5,"minecraft:magenta_stained_glass":3,"minecraft:red_glazed_terracotta":18,"minecraft:green_bed":2,"minecraft:beacon":101,"minecraft:stonecutter":8,"minecraft:chiseled_nether_bricks":32,"minecraft:cobblestone_slab":682,"minecraft:waxed_copper_block":3,"minecraft:glow_item_frame":37,"minecraft:polished_blackstone_pressure_plate":12,"minecraft:stripped_dark_oak_log":20,"minecraft:terracotta":20,"minecraft:music_disc_cat":2,"minecraft:dark_prismarine_slab":45,"minecraft:magenta_bed":1,"minecraft:yellow_stained_glass_pane":6,"minecraft:painting":351,"minecraft:magenta_carpet":54,"minecraft:infested_stone_bricks":21,"minecraft:smoker":7,"minecraft:warped_planks":1,"minecraft:dark_oak_door":1,"minecraft:purple_stained_glass":17,"minecraft:flower_pot":119,"minecraft:piston":7,"minecraft:netherite_block":18,"minecraft:wooden_hoe":45,"minecraft:command_block":170,"minecraft:cracked_polished_blackstone_bricks":43,"minecraft:gray_candle":2,"minecraft:map":37,"minecraft:detector_rail":12,"minecraft:cracked_nether_bricks":1,"minecraft:stone_slab":251,"minecraft:budding_amethyst":4,"minecraft:yellow_wool":93,"minecraft:stripped_crimson_hyphae":3,"minecraft:cobbled_deepslate_slab":26,"minecraft:chain_command_block":3,"minecraft:sea_pickle":43,"minecraft:polished_blackstone_button":129,"minecraft:smooth_stone":205,"minecraft:splash_potion":26,"minecraft:soul_torch":37,"minecraft:lime_candle":9},"minecraft:mined":{"minecraft:fire":2,"minecraft:grass":1,"minecraft:oak_log":5,"minecraft:tuff":4,"minecraft:ice":3}},"DataVersion":2865}